ZMC/ZMCintegral_functional.py
ZMC/ZMCintegral_multifunctions.py
ZMC/ZMCintegral_normal.py
ZMC/__init__.py
ZMCintegral-5.3.dist-info/LICENSE
ZMCintegral-5.3.dist-info/METADATA
ZMCintegral-5.3.dist-info/WHEEL
ZMCintegral-5.3.dist-info/top_level.txt
ZMCintegral-5.3.dist-info/RECORD
