Metadata-Version: 2.1
Name: ZMCintegral
Version: 5.3
Summary: An easy way to use multi-GPUs to calculate multi-dimensional integration
Home-page: https://github.com/Letianwu/ZMCintegral
Author: Cao Xiao-Yan, ZHANG Jun-Jie
Author-email: zjacob@mail.ustc.edu.cn
License: UNKNOWN
Platform: UNKNOWN
Classifier: Programming Language :: Python :: 3
Classifier: License :: OSI Approved :: Apache Software License
Classifier: Operating System :: POSIX :: Linux
Requires-Python: >=3.6
